maap_jupyter_server_extension/__init__.py
maap_jupyter_server_extension/_version.py
maap_jupyter_server_extension/constants.py
maap_jupyter_server_extension/handlers.py
maap_jupyter_server_extension/labextension/package.json
maap_jupyter_server_extension/labextension/static/lib_index_js.aa57df0cbe90212d688c.js
maap_jupyter_server_extension/labextension/static/lib_index_js.aa57df0cbe90212d688c.js.map
maap_jupyter_server_extension/labextension/static/remoteEntry.7c728b0c10d0af3af203.js
maap_jupyter_server_extension/labextension/static/remoteEntry.7c728b0c10d0af3af203.js.map
maap_jupyter_server_extension/labextension/static/style.js
maap_jupyter_server_extension/labextension/static/style_index_js.072a73dd49df0a87f3ce.js
maap_jupyter_server_extension/labextension/static/style_index_js.072a73dd49df0a87f3ce.js.map
maap_jupyter_server_extension-2.1.4.data/data/etc/jupyter/jupyter_server_config.d/dps_jupyter_server_extension.json
maap_jupyter_server_extension-2.1.4.data/data/share/jupyter/labextensions/maap-jupyter-server-extension/build_log.json
maap_jupyter_server_extension-2.1.4.data/data/share/jupyter/labextensions/maap-jupyter-server-extension/package.json
maap_jupyter_server_extension-2.1.4.data/data/share/jupyter/labextensions/maap-jupyter-server-extension/static/lib_index_js.aa57df0cbe90212d688c.js
maap_jupyter_server_extension-2.1.4.data/data/share/jupyter/labextensions/maap-jupyter-server-extension/static/lib_index_js.aa57df0cbe90212d688c.js.map
maap_jupyter_server_extension-2.1.4.data/data/share/jupyter/labextensions/maap-jupyter-server-extension/static/remoteEntry.7c728b0c10d0af3af203.js
maap_jupyter_server_extension-2.1.4.data/data/share/jupyter/labextensions/maap-jupyter-server-extension/static/remoteEntry.7c728b0c10d0af3af203.js.map
maap_jupyter_server_extension-2.1.4.data/data/share/jupyter/labextensions/maap-jupyter-server-extension/static/style.js
maap_jupyter_server_extension-2.1.4.dist-info/METADATA
maap_jupyter_server_extension-2.1.4.dist-info/WHEEL
maap_jupyter_server_extension-2.1.4.dist-info/licenses/LICENSE
maap_jupyter_server_extension-2.1.4.dist-info/RECORD
