Metadata-Version: 2.4
Name: maap_jupyter_server_extension
Version: 2.1.4
Dynamic: Keywords
Summary: A JupyterLab extension.
Project-URL: Homepage, https://github.com/MAAP-Project/jupyter-server-extension
Project-URL: Bug Tracker, https://github.com/MAAP-Project/jupyter-server-extension/issues
Project-URL: Repository, https://github.com/MAAP-Project/jupyter-server-extension.git
Author-email: Marjorie Lucas <marjorie.j.lucas@jpl.nasa.gov>
License:                                  Apache License
License-File: LICENSE
Classifier: Framework :: Jupyter
Classifier: Framework :: Jupyter :: JupyterLab
Classifier: Framework :: Jupyter :: JupyterLab :: 4
Classifier: Framework :: Jupyter :: JupyterLab :: Extensions
Classifier: Framework :: Jupyter :: JupyterLab :: Extensions :: Prebuilt
Classifier: License :: OSI Approved :: BSD License
Classifier: Programming Language :: Python
Classifier: Programming Language :: Python :: 3
Classifier: Programming Language :: Python :: 3.8
Classifier: Programming Language :: Python :: 3.9
Classifier: Programming Language :: Python :: 3.10
Classifier: Programming Language :: Python :: 3.11
Requires-Python: >=3.8
Requires-Dist: jupyter-nbextensions-configurator~=0.6.4
Requires-Dist: jupyter-server<2.13.0,>=2.0.1
Requires-Dist: nbformat~=5.10.3
Requires-Dist: notebook~=6.4.12
Requires-Dist: pytest~=8.1.1
Requires-Dist: pyyaml~=6.0.1
Requires-Dist: requests~=2.32.3
Requires-Dist: setuptools~=69.0
Requires-Dist: tornado~=6.4
Requires-Dist: xmltodict~=0.13.0
